catppuccin/__init__.py
catppuccin/models.py
catppuccin/palette.py
catppuccin/py.typed
catppuccin/extras/__init__.py
catppuccin/extras/matplotlib.py
catppuccin/extras/pygments.py
catppuccin/extras/rich_ctp.py
catppuccin/extras/matplotlib_styles/_catppuccin_template.txt
catppuccin/extras/matplotlib_styles/frappe.mplstyle
catppuccin/extras/matplotlib_styles/latte.mplstyle
catppuccin/extras/matplotlib_styles/macchiato.mplstyle
catppuccin/extras/matplotlib_styles/mocha.mplstyle
catppuccin-2.5.0.dist-info/METADATA
catppuccin-2.5.0.dist-info/WHEEL
catppuccin-2.5.0.dist-info/entry_points.txt
catppuccin-2.5.0.dist-info/licenses/LICENSE
catppuccin-2.5.0.dist-info/RECORD
