Metadata-Version: 2.4
Name: catppuccin
Version: 2.5.0
Summary: 🐍 Soothing pastel theme for Python.
Author-email: backwardspy <backwardspy@pigeon.life>
License-File: LICENSE
Requires-Python: >=3.9.0
Provides-Extra: gh-pages
Requires-Dist: pdoc>=15.0.1; extra == 'gh-pages'
Requires-Dist: tinycss2>=1.2.1; extra == 'gh-pages'
Provides-Extra: matplotlib
Requires-Dist: matplotlib>=3.8.4; extra == 'matplotlib'
Provides-Extra: pygments
Requires-Dist: pygments>=2.17.2; extra == 'pygments'
Provides-Extra: rich
Requires-Dist: rich>=13.7.0; extra == 'rich'
